sdutil/__init__.py
sdutil/__main__.py
sdutil/colorize.py
sdutil/fstree.py
sdutil/sdutil.py
sdutil-1.0.0.dist-info/LICENSE
sdutil-1.0.0.dist-info/METADATA
sdutil-1.0.0.dist-info/WHEEL
sdutil-1.0.0.dist-info/entry_points.txt
sdutil-1.0.0.dist-info/RECORD
