Metadata-Version: 2.1
Name: sdutil
Version: 1.0.0
Summary: Manage System Data files and local Time Machine snapshots on macOS.
Author: William Dye
Requires-Python: >=3.11,<4.0
Classifier: Programming Language :: Python :: 3
Classifier: Programming Language :: Python :: 3.11
Requires-Dist: treelib (>=1.7.1,<2.0.0)
